llm_ads/__init__.py
llm_ads/config.py
llm_ads/middleware.py
llm_ads/targeting.py
llm_ads/types.py
llm_ads/utils.py
llm_ads/core/__init__.py
llm_ads/core/database.py
llm_ads/models/__init__.py
llm_ads/models/ad.py
llm_ads/services/__init__.py
llm_ads/services/ad_analytics_service.py
llm_ads/services/config.py
llm_ads-0.1.7.dist-info/METADATA
llm_ads-0.1.7.dist-info/WHEEL
llm_ads-0.1.7.dist-info/top_level.txt
llm_ads-0.1.7.dist-info/RECORD
