Metadata-Version: 2.4
Name: llm-ads
Version: 0.1.7
Summary: FastAPI middleware for LLM ad serving integration
Author: Reasonic Team
Requires-Python: >=3.8
Requires-Dist: fastapi<0.110.0,>=0.109.0
Requires-Dist: pydantic>=2.7.0
Requires-Dist: starlette<0.37.0,>=0.36.0
Requires-Dist: sqlalchemy<2.1.0,>=2.0.0
Requires-Dist: asyncpg<0.30.0,>=0.29.0
Requires-Dist: python-dotenv<1.1.0,>=1.0.0
Requires-Dist: loguru<0.8.0,>=0.7.0
Requires-Dist: httpx<0.27.0,>=0.26.0
Requires-Dist: uvicorn<0.28.0,>=0.27.0
Requires-Dist: tenacity<8.4.0,>=8.3.0
Provides-Extra: dev
Requires-Dist: pytest>=7.4.0; extra == "dev"
Requires-Dist: pytest-asyncio>=0.21.0; extra == "dev"
Requires-Dist: black>=23.12.0; extra == "dev"
Requires-Dist: isort>=5.12.0; extra == "dev"
Requires-Dist: flake8>=6.1.0; extra == "dev"
Requires-Dist: mypy>=1.8.0; extra == "dev"
Dynamic: author
Dynamic: provides-extra
Dynamic: requires-dist
Dynamic: requires-python
Dynamic: summary
